TosKer-2.0.2.dist-info/DESCRIPTION.rst
TosKer-2.0.2.dist-info/METADATA
TosKer-2.0.2.dist-info/RECORD
TosKer-2.0.2.dist-info/WHEEL
TosKer-2.0.2.dist-info/entry_points.txt
TosKer-2.0.2.dist-info/metadata.json
TosKer-2.0.2.dist-info/top_level.txt
tosker/__init__.py
tosker/click_ui.py
tosker/docker_interface.py
tosker/helper.py
tosker/orchestrator.py
tosker/protocol_helper.py
tosker/storage.py
tosker/tosca_parser.py
tosker/graph/__init__.py
tosker/graph/artifacts.py
tosker/graph/nodes.py
tosker/graph/protocol.py
tosker/graph/relationships.py
tosker/graph/template.py
tosker/managers/__init__.py
tosker/managers/container_manager.py
tosker/managers/software_manager.py
tosker/managers/volume_manager.py
usr/share/tosker/tosker-types.yaml
usr/share/tosker/examples/node-mongo.csar
usr/share/tosker/examples/sockshop.csar
usr/share/tosker/examples/thinking.csar
