Metadata-Version: 2.0
Name: TosKer
Version: 2.0.2
Summary: A TOSCA engine working with Docker container
Home-page: https://github.com/di-unipi-socc/TosKer
Author: lucarin91
Author-email: to@lucar.in
License: MIT license
Keywords: docker TOSCA deployment management development
Platform: UNKNOWN
Classifier: Development Status :: 2 - Pre-Alpha
Classifier: Intended Audience :: Developers
Classifier: License :: OSI Approved :: MIT License
Classifier: Natural Language :: English
Classifier: Programming Language :: Python :: 2
Classifier: Programming Language :: Python :: 2.7
Classifier: Programming Language :: Python :: 3
Classifier: Programming Language :: Python :: 3.3
Classifier: Programming Language :: Python :: 3.4
Classifier: Programming Language :: Python :: 3.5
Classifier: Programming Language :: Python :: 3.6
Requires-Dist: docker
Requires-Dist: tosca-parser
Requires-Dist: termcolor
Requires-Dist: six
Requires-Dist: enum34
Requires-Dist: tabulate
Requires-Dist: tinydb
Requires-Dist: scandir
Requires-Dist: halo
Requires-Dist: click
Provides-Extra: dev
Requires-Dist: coverage; extra == 'dev'
Requires-Dist: check-manifest; extra == 'dev'
Requires-Dist: wheel; extra == 'dev'
Requires-Dist: flake8; extra == 'dev'
Requires-Dist: tox; extra == 'dev'
Requires-Dist: Sphinx; extra == 'dev'
Requires-Dist: isort; extra == 'dev'
